[{"meanings": [{"explanation": "vt.分裂，分离: to break apart or in two", "synonyms": "", "homonyms": "disassociate,disconnect,disjoin,disunite,divide,part,rend,rive,separate,sever,unyoke", "example": "", "antonyms": "bond,connect,join,link,unify,unite,yoke连接,结合"}], "english": "sunder"}, {"meanings": [{"explanation": "adj.高傲的，傲慢的: feeling or showing haughty disdain", "synonyms": "", "homonyms": "arrogant,assumptive,bumptious,haughty,imperious,pompous,presumptuous,overbearing,superior", "example": "", "antonyms": "humble,moderate,modest 谦逊的"}], "english": "supercilious"}, {"meanings": [{"explanation": "adj.表面的，肤浅的: lacking in depth, solidity, and comprehensiveness", "synonyms": "", "homonyms": "cursory,facile,perfunctory,shallow,sketchy,skin-deep", "example": "", "antonyms": "profound 深刻的,comprehensive,exhaustive 全面的"}], "english": "superficial"}, {"meanings": [{"explanation": "adj.多余的，过剩的: exceeding what is sufficient or necessary", "synonyms": "", "homonyms": "excessive,extra,redundant,surplus", "example": "", "antonyms": "deficient,inadeuate,insufficient,scanty,scarce,short,skimpy,sparse 不足的"}], "english": "superfluous"}, {"meanings": [{"explanation": "v.添声加色，使形象、某因素或性质更加清楚: to add as a distinct feature, element, or quality", "synonyms": "", "homonyms": "", "example": "", "antonyms": ""}], "english": "superimpose"}, {"meanings": [{"explanation": "adj.懒散的，懒得动的、倦怠的、消极的或漠不关心的: showing lethargy, passivity, or blameworthy indifference", "synonyms": "", "homonyms": "inert,passive,dormant,torpid", "example": "", "antonyms": "vi.gilant 警惕的"}], "english": "supine"}, {"meanings": [{"explanation": "adj.易弯曲的，柔软的: readily bent; pliant", "synonyms": "", "homonyms": "bendy,flexible,limber,lissome,lithe,pliable,pliant,lithesome", "example": "", "antonyms": "inflexible,stiff,rigid 坚硬"}], "english": "supple"}, {"meanings": [{"explanation": "vt.排挤，篡夺...的位置: to usurp the place of, especially through intrigue or underhanded tactics", "synonyms": "", "homonyms": "displace,displant,substitute,supersede,cut out", "example": "", "antonyms": ""}], "english": "supplant"}, {"meanings": [{"explanation": "n./v.增补，补充: something that serves to complete or make up for a deficiency in something else", "synonyms": "", "homonyms": "addendum,addition,expansion,increment,proliferation,step-up", "example": "", "antonyms": ""}], "english": "supplement"}, {"meanings": [{"explanation": "v.恳求，乞求: to make a request to (someone) in an earnest or urgent manner", "synonyms": "", "homonyms": "beseech,conjure,entreat,impetrate,implore,solicit,plead to,appeal to", "example": "", "antonyms": "demand 强求"}], "english": "supplicate"}, {"meanings": [{"explanation": "n.猜想，推测: an opinion or judgment based on little or no evidence", "synonyms": "", "homonyms": "hypothesis,proposition,surmise,premise,presumption", "example": "", "antonyms": "certainty 确定"}], "english": "supposition"}, {"meanings": [{"explanation": "vt.抑制(表情): to inhibit the expression of (an impulse, for example); check", "synonyms": "", "homonyms": "repress,smother,stifle,choke back,hold back", "example": "", "antonyms": "stimulate 激励"}, {"explanation": "v.用暴力终止，镇压: to put a stop to (something) by the use of force", "synonyms": "", "homonyms": "clamp down on,crack down on,put down,uash,repress,silence,slap down,snuff out,suash,suelch,subdue", "example": "", "antonyms": ""}], "english": "suppress"}, {"meanings": [{"explanation": "v./n.过高收费: to charge (someone) too much for goods or services", "synonyms": "", "homonyms": "gouge,soak,sting", "example": "", "antonyms": ""}], "english": "surcharge"}, {"meanings": [{"explanation": "v./n.过量，饮食过度: to feed or supply to excess", "synonyms": "", "homonyms": "overabundance,overage,overflow,plethora,redundancy,superfluity,surplus", "example": "", "antonyms": "deficiency,deprivation,insufficient supply,famish,starve 短缺,匮乏"}], "english": "surfeit"}, {"meanings": [{"explanation": "vt.交出，放弃，投降: to give (something) over to the control or possession of another usually under duress", "synonyms": "", "homonyms": "abnegate,cede,relinuish,renounce,resign", "example": "", "antonyms": "appropriate 挪用,占为己有"}, {"explanation": "v.沉溺于: to give (oneself) over to something especially unrestrainedly", "synonyms": "", "homonyms": "deliver,give up,indulge,yield", "example": "", "antonyms": ""}], "english": "surrender"}, {"meanings": [{"explanation": "adj.偷偷摸摸的，保密的: undertaken or done so as to escape being observed or known by others", "synonyms": "", "homonyms": "backstairs,clandestine,covert,furtive,privy,underground,underhanded,behind-the-scenes", "example": "", "antonyms": "barefaced,aboveboard,open,overt,public 光明正大的"}], "english": "surreptitious"}, {"meanings": [{"explanation": "n.易受感染的性质或状态: the quality or state of having little resistance to some outside agent", "synonyms": "", "homonyms": "defenselessness,vulnerability,weakness", "example": "", "antonyms": "immunity,invulnerability 免疫"}], "english": "susceptibility"}, {"meanings": [{"explanation": "vi.暂停，中止: to bring to a formal close for a period of time", "synonyms": "", "homonyms": "prorogue,recess", "example": "", "antonyms": "invoke 实行"}, {"explanation": "vt.悬挂: hang", "synonyms": "", "homonyms": "", "example": "", "antonyms": "erect,let fall使直立,落下"}], "english": "suspend"}, {"meanings": [{"explanation": "n./v.缝合: the process of joining two surfaces or edges together along a line by or as if by sewing", "synonyms": "", "homonyms": "", "example": "", "antonyms": "incision,avulse 切开,撕脱"}], "english": "suture"}, {"meanings": [{"explanation": "adj.(女人)体态苗条的，优雅的: slender or graceful in figure or outline; slim.", "synonyms": "", "homonyms": "bony,lean,skinny,slender,slim", "example": "", "antonyms": "plump,corpulent,paunchy and awkward丰满的,大腹便便而笨拙的"}], "english": "svelte"}, {"meanings": [{"explanation": "vi.大摇大摆地走，趾高气昂地走: to conduct oneself in an arrogant or superciliously pompous manner", "synonyms": "", "homonyms": "prance,sashay,stalk", "example": "", "antonyms": ""}, {"explanation": "v.自夸，吹嘘: boast, brag", "synonyms": "", "homonyms": "brag,vapor,vaunt,gasconade", "example": "", "antonyms": ""}], "english": "swagger"}, {"meanings": [{"explanation": "vi.咒骂: to use profane or obscene language: curse", "synonyms": "", "homonyms": "blaspheme,curse,cuss", "example": "", "antonyms": "accolade 赞美"}, {"explanation": "v.宣誓: to promise or pledge with a solemn oath; vow", "synonyms": "", "homonyms": "attest,depose,covenant,pledge,vow", "example": "", "antonyms": ""}], "english": "swear"}, {"meanings": [{"explanation": "adj.酷热的: oppressively hot", "synonyms": "", "homonyms": "boiling,scorching,searing,sultry,torrid,fiery", "example": "", "antonyms": "algid,arctic,bone-chilling,freezing,frigid,frozen,glacial,ice-cold,iced,icy 严寒的"}], "english": "sweltering"}, {"meanings": [{"explanation": "vi.突然改变方向: to turn aside abruptly from a straight line or course", "synonyms": "", "homonyms": "detour,deviate,diverge,sheer,swing,veer", "example": "", "antonyms": "maintain direction,straighten 保持方向,直行"}], "english": "swerve"}, {"meanings": [{"explanation": "vt.痛饮，大口地吃: to drink greedily, to eat greedily or to excess", "synonyms": "", "homonyms": "gulp,uaff,swig", "example": "", "antonyms": "sip 啜饮"}], "english": "swill"}, {"meanings": [{"explanation": "vt.欺骗，骗取: to cheat or defraud of money or property", "synonyms": "", "homonyms": "bilk,con,hustle,fiddle,gyp,bunco,flimflam", "example": "", "antonyms": ""}], "english": "swindle"}, {"meanings": [{"explanation": "n.沉于奢侈逸乐者，酒色之徒: a person devoted to pleasure and luxury; a voluptuary", "synonyms": "", "homonyms": "debauchee,decadent,hedonist,sensualist", "example": "", "antonyms": "spartan,ascetic 禁欲者"}], "english": "sybarite"}, {"meanings": [{"explanation": "n.马屁精: a servile self-seeking flatterer", "synonyms": "", "homonyms": "fawner,flunky,lickspittle,toady,apple-polisher,bootlicker,brownnoser", "example": "", "antonyms": ""}], "english": "sycophant"}, {"meanings": [{"explanation": "n.提纲，摘要: 课文、演讲或研究课题的要点的概要或提纲: an outline or a summary of the main points of a text, lecture, or course of study", "synonyms": "", "homonyms": "", "example": "", "antonyms": ""}], "english": "syllabus"}, {"meanings": [{"explanation": "n.由一般到个别的推理；演绎: reasoning from the general to the specific; deduction", "synonyms": "", "homonyms": "", "example": "", "antonyms": ""}], "english": "syllogism"}, {"meanings": [{"explanation": "n.共生关系: the living together in more or less intimate association or close union of two dissimilar", "synonyms": "", "homonyms": "", "example": "", "antonyms": "unrelated growth 无关联的生长"}], "english": "symbiosis"}, {"meanings": [{"explanation": "n.对称: balanced proportions", "synonyms": "", "homonyms": "balance,coherence,consonance,proportion", "example": "", "antonyms": "disproportion,asymmetry,discordance,disproportion,disunity,imbalance,incoherence,violence 不均衡,混乱"}], "english": "symmetry"}, {"meanings": [{"explanation": "adj. 同时期的，同相的: having identical period and phase", "synonyms": "", "homonyms": "coetaneous,coeval,coexistent,concurrent,contemporaneous,simultaneous", "example": "", "antonyms": "occurring at different times,noncontemporaneous,out-of-phase 发生在不同时代的"}], "english": "synchronous"}, {"meanings": [{"explanation": "adj.合作的: working together: cooperating", "synonyms": "", "homonyms": "", "example": "", "antonyms": "antagonistic 敌对的"}], "english": "synergic"}, {"meanings": [{"explanation": "adj.同义的: having the same or a similar meaning", "synonyms": "", "homonyms": "", "example": "", "antonyms": ""}], "english": "synonymous"}, {"meanings": [{"explanation": "n.摘要，概要: a brief outline or general view; an abstract or a summary.", "synonyms": "", "homonyms": "abstract,brief,digest,recapitulation,roundup,summarization,epitome", "example": "", "antonyms": ""}], "english": "synopsis"}, {"meanings": [{"explanation": "n.合成，综合: the combination of parts or elements so as to form a whole", "synonyms": "", "homonyms": "admixture,alloy,amalgamation,compound,conflation,fusion,meld", "example": "", "antonyms": "analysis,take apart 分解"}], "english": "synthesis"}, {"meanings": [{"explanation": "adj.暗示的: implied or indicated (as by an act or by silence) but not actually expressed", "synonyms": "", "homonyms": "implied,unexpressed,unspoken,unvoiced,wordless", "example": "", "antonyms": "explicit,express,expressed,spoken,stated,voiced 明确的表达,直率的"}], "english": "tacit"}, {"meanings": [{"explanation": "adj.沉默寡言的，话少的: temperamentally disinclined to talk", "synonyms": "", "homonyms": "laconic,reserved,reticent,tight-lipped,uncommunicative", "example": "", "antonyms": "garrulous,louacious,glib,expansive,prolix,voluble 多话的"}], "english": "taciturn"}, {"meanings": [{"explanation": "v.着手处理: to start work on energetically", "synonyms": "", "homonyms": "dive into,wade in", "example": "", "antonyms": ""}], "english": "tackle"}, {"meanings": [{"explanation": "n.机敏，精明，不冒犯: a keen sense of what to do or say in order to maintain good relations with others or avoid offense", "synonyms": "", "homonyms": "diplomacy", "example": "", "antonyms": "clumsiness,insensitivity,tactlessness 笨拙"}], "english": "tact"}, {"meanings": [{"explanation": "adj.有触觉的，能触知的: perceptible by touch: tangible", "synonyms": "", "homonyms": "", "example": "", "antonyms": ""}], "english": "tactile"}, {"meanings": [{"explanation": "adj.不机智的，笨拙的: bluntly inconsiderate or indiscreet.", "synonyms": "", "homonyms": "graceless,ill-advised,imprudent,indelicate,injudicious,undiplomatic", "example": "", "antonyms": "advisable,discreet,judicious,prudent,tactful,wise小心谨慎的,明智的"}], "english": "tactless"}, {"meanings": [{"explanation": "n.护身符: something worn or kept to bring good luck or keep away evil", "synonyms": "", "homonyms": "amulet,fetish,mascot,mojo,periapt,phylactery", "example": "", "antonyms": ""}], "english": "talisman"}, {"meanings": [{"explanation": "vt.(品质)、污损: to affect slightly with something morally bad or undesirable", "synonyms": "", "homonyms": "blemish,darken,mar,spoil,tarnish,vitiate", "example": "", "antonyms": ""}], "english": "taint"}, {"meanings": [{"explanation": "vi.恶意窜改，损害: to handle thoughtlessly, ignorantly, or mischievously", "synonyms": "", "homonyms": "diddle with,fiddle with,fool with,mess with", "example": "", "antonyms": ""}, {"explanation": "v.玩弄: to tinker with rashly or foolishly", "synonyms": "", "homonyms": "", "example": "", "antonyms": ""}], "english": "tamper"}, {"meanings": [{"explanation": "n. / adj.离题(的)，不相关(的): diverging from an original purpose of course: irrelevant", "synonyms": "", "homonyms": "excursive,digressive", "example": "", "antonyms": "essential重要的"}], "english": "tangent"}, {"meanings": [{"explanation": "adj.可感知的: capable of being perceived", "synonyms": "", "homonyms": "palpable,touchable", "example": "", "antonyms": "impalpable,intangible,unable to perceive无法感知的"}, {"explanation": "adj.确凿的，真实的: possible to be treated as fact; real or concrete", "synonyms": "", "homonyms": "", "example": "", "antonyms": ""}], "english": "tangible"}, {"meanings": [{"explanation": "adj.剌激的: having a powerfully stimulating odor or flavor", "synonyms": "", "homonyms": "pungent,strong", "example": "", "antonyms": "bland,mild,smooth 不剌激的"}], "english": "tangy"}, {"meanings": [{"explanation": "vt.激起，挑逗: to excite (another) by exposing something desirable while keeping it out of reach", "synonyms": "", "homonyms": "", "example": "", "antonyms": "comfort,console,solace,alleviate,assuage,relieve,satiate 安慰,缓和"}], "english": "tantalize"}, {"meanings": [{"explanation": "adj.等价的，与...相等的: equivalent in value, significance, or effect", "synonyms": "", "homonyms": "", "example": "", "antonyms": "incommensurate 不相称的"}], "english": "tantamount"}, {"meanings": [{"explanation": "n.勃然大怒，发脾气: a fit of bad temper", "synonyms": "", "homonyms": "blowup,explosion,fit", "example": "", "antonyms": "pacification 平静"}], "english": "tantrum"}, {"meanings": [{"explanation": "vt.(使)逐渐变细: to become gradually narrower or thinner toward one end", "synonyms": "", "homonyms": "abate,decline,diminish,dwindle,shrink,wane,drain away", "example": "", "antonyms": ""}, {"explanation": "v.逐渐减少，减弱: to diminish or lessen gradually", "synonyms": "", "homonyms": "subside,die down,phase down,fall away,let up", "example": "", "antonyms": ""}], "english": "taper"}, {"meanings": [{"explanation": "adj.缓慢的，迟缓的: moving slowly: sluggish", "synonyms": "", "homonyms": "crawling,creeping,dallying,dawdling,dilatory,dragging,lagging,languid,sluggish", "example": "", "antonyms": "bolting,brisk,fleet,flying,meteoric,rocketing,scooting,scudding,scurrying,swift,whirling 迅速的"}, {"explanation": "adj.延后的，迟的: delayed beyond the expected or proper time", "synonyms": "", "homonyms": "behind,belated,delinuent,overdue", "example": "", "antonyms": "early,inopportune,precocious,premature,unseasonable,untimely 提早的"}], "english": "tardy"}, {"meanings": [{"explanation": "vt.玷污: to affect slightly with something morally bad or undesirable", "synonyms": "", "homonyms": "blemish,mar,stain,vitiate", "example": "", "antonyms": ""}], "english": "tarnish"}, {"meanings": [{"explanation": "adj.美味的，令人愉悦的: giving pleasure or contentment to the mind or senses", "synonyms": "", "homonyms": "agreeable,delectable,delightful,satisfying,savory", "example": "", "antonyms": "uninteresting,disagreeable,unpalatable,unpleasant,unwelcome 无趣的,令人失望的"}], "english": "tasty"}, {"meanings": [{"explanation": "adj.破旧的，褴褛的: somewhat worn, shabby, or dilapidated", "synonyms": "", "homonyms": "dilapidated,scruffy,seedy,sleazy,tatterdemalion,tatty,threadbare", "example": "", "antonyms": "smart 漂亮的"}], "english": "tatty"}, {"meanings": [{"explanation": "vt.嘲弄性质疑，挑衅: to reproach or challenge in a mocking or insulting manner: jeer at", "synonyms": "", "homonyms": "bait,hassle,haze,heckle,needle,ride", "example": "", "antonyms": ""}], "english": "taunt"}, {"meanings": [{"explanation": "adj.紧绷的: not loose or flabby", "synonyms": "", "homonyms": "", "example": "", "antonyms": "lax,loose,slack 松弛的"}, {"explanation": "adj.整洁的: kept in proper order or condition, kept in trim shape; neat and tidy", "synonyms": "", "homonyms": "kempt,orderly,shipshape,trim", "example": "", "antonyms": ""}], "english": "taut"}, {"meanings": [{"explanation": "adj.俗丽的: cheap and gaudy in appearance or quality; ignoble", "synonyms": "", "homonyms": "meretricious,gaudy,flashy,garish", "example": "", "antonyms": "exuisite高雅的"}], "english": "tawdry"}, {"meanings": [{"explanation": "adj.繁重的，费力的: requiring much time, effort, or careful attention", "synonyms": "", "homonyms": "arduous,burdensome,exacting,grueling,laborious,onerous,toilsome", "example": "", "antonyms": "light,easy 轻快的"}], "english": "taxing"}, {"meanings": [{"explanation": "adj.冗长乏味的: tiresome because of length or dullness: boring", "synonyms": "", "homonyms": "drab,dreary,jading,monotonous,stale,stodgy,stuffy,weary,drudging", "example": "", "antonyms": "entertaining,absorbing,stimulating,engaging,engrossing,gripping,interesting,intriguing,involving,riveting令人愉快的,吸引人的"}], "english": "tedious"}, {"meanings": [{"explanation": "vi.蹒跚，不稳定的行走: to move unsteadily: wobble", "synonyms": "", "homonyms": "careen,dodder,lurch,reel", "example": "", "antonyms": "stabilize使...稳固"}, {"explanation": "v.犹豫不决: to show uncertainty about the right course of action", "synonyms": "", "homonyms": "balance,dither,falter,hang back,scruple,shilly-shally,stagger,vacillate,waver,wobble", "example": "", "antonyms": "dive in,plunge in"}], "english": "teeter"}, {"meanings": [{"explanation": "n.禁酒: the principle or practice of complete abstinence from alcoholic drinks", "synonyms": "", "homonyms": "", "example": "", "antonyms": "intemperance饮酒过度"}], "english": "teetotalism"}, {"meanings": [{"explanation": "adj.有效的，显著的: effective, expressive", "synonyms": "", "homonyms": "compelling,conclusive,convincing,forceful,persuasive,satisfying", "example": "", "antonyms": "inconclusive,indecisive,ineffective,uncompelling,unconvincing,unpersuasive 无效的"}], "english": "telling"}, {"meanings": [{"explanation": "n.鲁莽，冒失: foolhardy disregard of danger; recklessness", "synonyms": "", "homonyms": "audacity,brashness,presumption,presumptuousness", "example": "", "antonyms": "circumspection,cautious approach,pusillanimity 谨慎"}], "english": "temerity"}, {"meanings": [{"explanation": "v.行动躲躲闪闪以争取时间、躲避争论等: to act evasively in order to gain time, avoid argument, or postpone a decision", "synonyms": "", "homonyms": "", "example": "", "antonyms": ""}], "english": "temporize"}, {"meanings": [{"explanation": "adj.言行举止有分寸的: avoiding extremes in behavior or expression", "synonyms": "", "homonyms": "", "example": "", "antonyms": "immoderate,extreme,frivolous 极端的"}, {"explanation": "adj.有节制的: given to or marked by restraint in the satisfaction of one's appetites", "synonyms": "", "homonyms": "abstentious,abstinent,continent,self-abnegating,self-denying,sober", "example": "", "antonyms": "self-indulgent放纵的"}], "english": "temperate"}, {"meanings": [{"explanation": "adj.突然且剧烈的变化: marked by sudden or violent disturbance", "synonyms": "", "homonyms": "cataclysmal,tumultuous,turbulent", "example": "", "antonyms": "serene 平静的"}], "english": "tempestuous"}, {"meanings": [{"explanation": "adj.有据可依的，无懈可击的: capable of being held or defended; reasonable", "synonyms": "", "homonyms": "defendable,justifiable,maintainable,supportable,sustainable", "example": "", "antonyms": "unjustified,unsound,specious,indefensible,fallacious 不合理的"}], "english": "tenable"}, {"meanings": [{"explanation": "adj.顽固的，不屈不挠的: persistent in maintaining something valued or habitual", "synonyms": "", "homonyms": "dogged,insistent,persevering,pertinacious", "example": "", "antonyms": "n.egotiable,vacillated 可商量的,踌躇的"}, {"explanation": "adj.粘着的: tending to adhere to objects upon contact", "synonyms": "", "homonyms": "adherent,adhesive,clingy,glutinous,tacky,viscid", "example": "", "antonyms": "n.onadhesive不具有粘性的"}], "english": "tenacious"}, {"meanings": [{"explanation": "adj.有偏见的: marked by a tendency in favor of a particular point of view: biased", "synonyms": "", "homonyms": "partial,distorting,subjective,biased", "example": "", "antonyms": "unbiased,unprejudiced 公平的"}], "english": "tendentious"}, {"meanings": [{"explanation": "vt.正式提出: to offer formally", "synonyms": "", "homonyms": "extend,proffer,trot out", "example": "", "antonyms": "withdraw撤回"}, {"explanation": "adj.考虑周到的，关心同情的: having or marked by sympathy and consideration for others", "synonyms": "", "homonyms": "beneficent,benevolent,benignant,compassionate,softhearted", "example": "", "antonyms": "atrocious,barbarous,bestial,brutal,callous,cruel,fiendish,inhuman,insensate,sadistic,savage,truculent,uncompassionate,vicious尖酉麦刻薄的"}], "english": "tender"}, {"meanings": [{"explanation": "adj.没有实际内容的: having little substance; flimsy", "synonyms": "", "homonyms": "", "example": "", "antonyms": "substantial 实质的"}], "english": "tenuous"}, {"meanings": [{"explanation": "adj.不太热心的: showing little or no interest or enthusiasm", "synonyms": "", "homonyms": "lukewarm,halfhearted,uneager,unenthusiastic", "example": "", "antonyms": "ardent,ebullient,feverish,keen,passionate,wholehearted 热心的 terminology"}], "english": "tepid"}, {"meanings": [{"explanation": "n.专业术语: the special terms or expressions of a particular group or field", "synonyms": "", "homonyms": "argot,cant,dialect,jargon,jive,lingo,patois,patter,slang", "example": "", "antonyms": ""}], "english": "terminology"}, {"meanings": [{"explanation": "n.终点，终点站: the final point; the end", "synonyms": "", "homonyms": "", "example": "", "antonyms": "outset,sustain开始,持续"}], "english": "terminus"}, {"meanings": [{"explanation": "n.极度恐惧: a state of intense fear", "synonyms": "", "homonyms": "anxiety,dread,fearfulness,fright,horror,panic,trepidation", "example": "", "antonyms": ""}], "english": "terror"}, {"meanings": [{"explanation": "adj.简洁的，简明的: brief and to the point; effectively concise", "synonyms": "", "homonyms": "compact,compendious,laconic,pithy,succinct", "example": "", "antonyms": "circuitous,circumlocutory,diffuse,long-winded,prolix,rambling,verbose,windy,wordy 冗长啰嗦的"}], "english": "terse"}, {"meanings": [{"explanation": "n.证词，声明: firsthand authentication of a fact", "synonyms": "", "homonyms": "attestation,confirmation,documentation,substantiation,testament,validation", "example": "", "antonyms": "disproof 反驳"}], "english": "testimony"}, {"meanings": [{"explanation": "adj.易怒的，暴躁的: easily annoyed: irritable", "synonyms": "", "homonyms": "choleric,irascible,peevish,perverse,pettish,petulant", "example": "", "antonyms": "affable,good humor,unable to irritate,imperturbable,patient 和蔼可亲的,冷静的,忍耐的"}], "english": "testy"}, {"meanings": [{"explanation": "vt.(用绳，铁链)拴系，束缚: to fasten or restrain by or as if by a tether", "synonyms": "", "homonyms": "", "example": "", "antonyms": "detach,tear loose分开,撕裂"}, {"explanation": "n.能力或忍耐力的极限: the limit of one's strength or resources", "synonyms": "", "homonyms": "", "example": "", "antonyms": ""}], "english": "tether"}, {"meanings": [{"explanation": "adj.做作的，夸张的，矫揉造作的: marked by exaggerated self-display and unnatural behavior", "synonyms": "", "homonyms": "dramatic,histrionic,melodramatic,stagy", "example": "", "antonyms": "n.atural,understated,reserved,restraint 自然的"}], "english": "theatrical"}, {"meanings": [{"explanation": "adj.治疗的: of or relating to the treatment of disease or disorders by remedial agents or methods", "synonyms": "", "homonyms": "curative,healing,officinal,remedial,restorative", "example": "", "antonyms": ""}], "english": "therapeutic"}, {"meanings": [{"explanation": "adj.多剌的: full of thorns", "synonyms": "", "homonyms": "", "example": "", "antonyms": "smooth 平滑的"}, {"explanation": "adj.棘手的: full of difficulties or controversial points : ticklish", "synonyms": "", "homonyms": "catchy,delicate,knotty,prickly,ticklish", "example": "", "antonyms": ""}], "english": "thorny"}, {"meanings": [{"explanation": "adj.陈腐的: overused to the point of being worn out; hackneved", "synonyms": "", "homonyms": "banal,cliche,commonplace,hackney,shopworn,trite", "example": "", "antonyms": ""}, {"explanation": "adj.贫穷的: lacking money or material possessions", "synonyms": "", "homonyms": "beggared,destitute,down-and-out,famished,impecunious,impoverished,indigent,necessitous,needful,pauperized,penniless,penurious,poverty-stricken,skint", "example": "", "antonyms": "affluent,deep-pocketed,flush,opulent,silk-stocking,wealthy,well-heeled,well-off,well-to-do 富裕的"}, {"explanation": "adj.破烂的: worn or torn into or as if into rags", "synonyms": "", "homonyms": "frayed,raggedy,ratty,seedy,shabby,tattered,worn-out", "example": "", "antonyms": ""}], "english": "threadbare"}, {"meanings": [{"explanation": "vi. /n.大量聚集: to crowd together in great numbers", "synonyms": "", "homonyms": "flock,mob,swarm", "example": "", "antonyms": ""}], "english": "throng"}, {"meanings": [{"explanation": "vt.阻挠: to oppose successfully", "synonyms": "", "homonyms": "baffle,balk,checkmate,discomfit", "example": "", "antonyms": "advance,cultivate,encourage,forward,foster,further,nurture,promote,support,aid,bolster,abet,foment,facilitate促进,支持"}], "english": "thwart"}, {"meanings": [{"explanation": "adj.易怒的: easily offended or upset; touchy", "synonyms": "", "homonyms": "huffy,tetchy,thin-skinned", "example": "", "antonyms": "imperturbable镇静的"}, {"explanation": "adj.棘手的，对技巧要求高的: requiring exceptional skill or caution in performance or handling", "synonyms": "", "homonyms": "catchy,delicate,difficult,dodgy,knotty,prickly,problematic,sensitive,spiny,sticky,thorny,touchy,tough,tricksy", "example": "", "antonyms": ""}], "english": "ticklish"}, {"meanings": [{"explanation": "n./v.小争吵: a petty quarrel", "synonyms": "", "homonyms": "altercate,bicker,brabble,hassle,uarrel,uibble,row,scrap,spat,suabble", "example": "", "antonyms": ""}], "english": "tiff"}, {"meanings": [{"explanation": "adj.吝啬的: close-fisted; stingy", "synonyms": "", "homonyms": "mean,miserly,parsimonious,penurious,sparing,stinting", "example": "", "antonyms": "bounteous,bountiful,charitable,freehanded,generous,liberal,munificent,openhanded,unsparing,unstinting 慷慨大方的"}], "english": "tightfisted"}, {"meanings": [{"explanation": "adj.陈腐的: hackneyed, stale", "synonyms": "", "homonyms": "banal,cliche,commonplace,hackneyed,stereotyped,threadbare,trite", "example": "", "antonyms": "fresh,new,novel,original,uncliched,unhackneyed 新奇的"}], "english": "timeworn"}, {"meanings": [{"explanation": "adj.胆小的，不自信的: lacking in courage or self-confidence", "synonyms": "", "homonyms": "fainthearted,fearsome,scary,timorous,tremulous", "example": "", "antonyms": "stalwart,adventurous,audacious,bold,daring,dashing,gutsy,venturous 坚定勇敢的"}], "english": "timid"}, {"meanings": [{"explanation": "adj.胆小的: of a timid disposition: fearful", "synonyms": "", "homonyms": "timid,undaring,uailing,recoiling,scary,skittish", "example": "", "antonyms": "stalwart,intrepid,adventurous,audacious,bold,daring,dashing,gutsy,venturous大胆的"}], "english": "timorous"}, {"meanings": [{"explanation": "vt.给...着上少量的色彩: to color with a slight shade or stain; tint", "synonyms": "", "homonyms": "dye,pigment,stain,tincture,tint", "example": "", "antonyms": "suffuse,decolorize遍染,使脱色"}], "english": "tinge"}, {"meanings": [{"explanation": "vi.乱修，乱调整: to handle thoughtlessly, ignorantly, or mischievously", "synonyms": "", "homonyms": "diddle with,fiddle with,fool with,mess with,toy with,twiddle with", "example": "", "antonyms": "adj.ust,repair调整,修理"}], "english": "tinker"}, {"meanings": [{"explanation": "v.涂浅色，微染: apply a usually slight or pale coloration to", "synonyms": "", "homonyms": "dye,pigment,stain,tincture,tinge", "example": "", "antonyms": "suffuse,decolorize遍染,使脱色"}], "english": "tint"}, {"meanings": [{"explanation": "n.长篇抨击性演讲: a long angry or violent speech, usually of a censorious or denunciatory nature; a diatribe", "synonyms": "", "homonyms": "harangue,diatribe,jeremiad,philippic,rant", "example": "", "antonyms": "eulogy,encomium,panegyric,tribute 颂词"}], "english": "tirade"}, {"meanings": [{"explanation": "n./v.马屁精，拍马屁: one who flatters in the hope of gaining favors", "synonyms": "", "homonyms": "sycophant,groveler,flatterer", "example": "", "antonyms": ""}], "english": "toady"}, {"meanings": [{"explanation": "adj.滋补的，有益健康的: producing or stimulating physical, mental, or emotional vigor; beneficial to the health of body or mind", "synonyms": "", "homonyms": "medicinal,restorative,salubrious,salutary,salutiferous,sanative,wholesome", "example": "", "antonyms": "insalubrious,noxious,unhealthful,unhealthy,unwholesome 不健康的"}], "english": "tonic"}]